climatrix/__init__.py
climatrix/_version.py
climatrix/comparison.py
climatrix/exceptions.py
climatrix/io.py
climatrix/models.py
climatrix/types.py
climatrix/warnings.py
climatrix/cli/__init__.py
climatrix/cli/dataset.py
climatrix/cli/main.py
climatrix/dataset/__init__.py
climatrix/dataset/axis.py
climatrix/dataset/base.py
climatrix/dataset/consts.py
climatrix/dataset/domain.py
climatrix/dataset/utils.py
climatrix/decorators/__init__.py
climatrix/decorators/operators.py
climatrix/decorators/runtime.py
climatrix/optim/__init__.py
climatrix/optim/bayesian.py
climatrix/plot/__init__.py
climatrix/plot/core.py
climatrix/reconstruct/__init__.py
climatrix/reconstruct/base.py
climatrix/reconstruct/idw.py
climatrix/reconstruct/kriging.py
climatrix/reconstruct/type.py
climatrix/reconstruct/sinet/__init__.py
climatrix/reconstruct/sinet/callbacks.py
climatrix/reconstruct/sinet/dataset.py
climatrix/reconstruct/sinet/losses.py
climatrix/reconstruct/sinet/model.py
climatrix/reconstruct/sinet/sinet.py
climatrix/reconstruct/sinet/resources/lat_lon_elevation.npy
climatrix/reconstruct/siren/__init__.py
climatrix/reconstruct/siren/dataset.py
climatrix/reconstruct/siren/losses.py
climatrix/reconstruct/siren/model.py
climatrix/reconstruct/siren/siren.py
climatrix/resources/logging.ini
climatrix/resources/scripts/download/cds/e-obs.toml
climatrix/resources/scripts/download/cds/era5-land.toml
climatrix/resources/scripts/download/ecad/blend_mean_temperature.sh
climatrix/resources/scripts/download/ecad/nonblend_mean_temperature.sh
climatrix/resources/scripts/download/hadisd/download_air_temperature.sh
climatrix/resources/scripts/plotting/finding_surface_by_normals.py
climatrix/resources/scripts/test/_test_kriging.py
climatrix/resources/scripts/test/_test_siren.py
climatrix/resources/scripts/test/test_accessor.py
climatrix/resources/scripts/test/test_add.py
climatrix/resources/scripts/test/test_domain_from_latlon.py
climatrix/resources/scripts/test/test_idw.py
climatrix-1.1.0.dev0.dist-info/licenses/LICENSE
climatrix-1.1.0.dev0.dist-info/METADATA
climatrix-1.1.0.dev0.dist-info/WHEEL
climatrix-1.1.0.dev0.dist-info/entry_points.txt
climatrix-1.1.0.dev0.dist-info/top_level.txt
climatrix-1.1.0.dev0.dist-info/RECORD
