Metadata-Version: 2.4
Name: climatrix
Version: 1.1.0.dev0
Summary: Tool for climate data research
Author-email: Jakub Walczak <jakub.walczak@p.lodz.pl>, Wojciech Żyndul <242575@edu.p.lodz.pl>
Keywords: climate data
Requires-Python: >=3.12
License-File: LICENSE
Requires-Dist: numpy
Requires-Dist: xarray
Requires-Dist: matplotlib
Requires-Dist: seaborn
Requires-Dist: netCDF4
Requires-Dist: cartopy
Requires-Dist: typer
Requires-Dist: rich
Requires-Dist: setuptools
Requires-Dist: scipy
Requires-Dist: tqdm
Provides-Extra: dev
Requires-Dist: cdsapi>=0.7.4; extra == "dev"
Requires-Dist: isort; extra == "dev"
Requires-Dist: black; extra == "dev"
Requires-Dist: pre-commit; extra == "dev"
Requires-Dist: autoflake; extra == "dev"
Requires-Dist: pytest; extra == "dev"
Provides-Extra: docs
Requires-Dist: mkdocs; extra == "docs"
Requires-Dist: mkdocs-material; extra == "docs"
Requires-Dist: mike; extra == "docs"
Requires-Dist: mkdocs-awesome-pages-plugin; extra == "docs"
Requires-Dist: mkdocs-git-revision-date-localized-plugin; extra == "docs"
Requires-Dist: mkdocs-glightbox; extra == "docs"
Requires-Dist: pymdown-extensions; extra == "docs"
Requires-Dist: mkdocstrings[python]; extra == "docs"
Provides-Extra: ml
Requires-Dist: torch; extra == "ml"
Requires-Dist: scikit-learn; extra == "ml"
Provides-Extra: plot
Requires-Dist: flask; extra == "plot"
Provides-Extra: optim
Requires-Dist: bayesian-optimization; extra == "optim"
Provides-Extra: ok
Requires-Dist: pykrige; extra == "ok"
Provides-Extra: all
Requires-Dist: climatrix[dev]; extra == "all"
Requires-Dist: climatrix[ml]; extra == "all"
Requires-Dist: climatrix[optim]; extra == "all"
Requires-Dist: climatrix[ok]; extra == "all"
Requires-Dist: climatrix[plot]; extra == "all"
Dynamic: license-file
